cloudmesh_cmsd/__init__.py
cloudmesh_cmsd/cmsd/__init__.py
cloudmesh_cmsd/cmsd/__version__.py
cloudmesh_cmsd/cmsd/command/Dockerfile
cloudmesh_cmsd/cmsd/command/__init__.py
cloudmesh_cmsd/cmsd/command/cmsd.py
cloudmesh_cmsd/cmsd/command/init.sh
cloudmesh_cmsd-4.2.18.dist-info/LICENSE
cloudmesh_cmsd-4.2.18.dist-info/METADATA
cloudmesh_cmsd-4.2.18.dist-info/WHEEL
cloudmesh_cmsd-4.2.18.dist-info/entry_points.txt
cloudmesh_cmsd-4.2.18.dist-info/top_level.txt
cloudmesh_cmsd-4.2.18.dist-info/RECORD
